pyviewercloud-0.2.1.dist-info/METADATA
pyviewercloud-0.2.1.dist-info/WHEEL
pyviewercloud/__init__.py
pyviewercloud/test.py
pyviewercloud/pyviewercloud.cpython-36m-darwin.so
pyviewercloud-0.2.1.dist-info/RECORD
