Metadata-Version: 2.1
Name: pyviewercloud
Version: 0.2.1
Summary: Python bindings for viewercloud
Keywords: python
Home-Page: https://github.com/ThomAub/viewercloud
Author: Thomaub <github.thomaub@gmail.com>
Author-Email: Thomaub <github.thomaub@gmail.com>
License: MIT
